MANIFEST.in
README.rst
senderbase.py
setup.cfg
setup.py
senderbase.egg-info/PKG-INFO
senderbase.egg-info/SOURCES.txt
senderbase.egg-info/dependency_links.txt
senderbase.egg-info/pbr.json
senderbase.egg-info/requires.txt
senderbase.egg-info/top_level.txt
tests/test_senderbase.py
tests/mocks/192.168.0.1_result.html
tests/mocks/4.4.4.4_result.html
tests/mocks/8.8.8.8_result.html
tests/mocks/a.b.c.d_result.html
tests/mocks/amazon.com_domain_result.html
tests/mocks/amazon.com_multiple_result.html
tests/mocks/google.com_result.html