Metadata-Version: 1.1
Name: senderbase
Version: 0.2
Summary: A screen scraper for the senderbase.org website
Home-page: https://github.com/meatheadmike/senderbase
Author: Mike Skovgaard
Author-email: mikesk@gmail.com
License: MIT
Keywords: senderbase development email spam
Platform: UNKNOWN
Classifier: Development Status :: 3 - Alpha
Classifier: Intended Audience :: Developers
Classifier: License :: OSI Approved :: MIT License
Classifier: Programming Language :: Python :: 2
Classifier: Programming Language :: Python :: 2.6
Classifier: Programming Language :: Python :: 2.7
Classifier: Programming Language :: Python :: 3
Classifier: Programming Language :: Python :: 3.2
Classifier: Programming Language :: Python :: 3.3
Classifier: Programming Language :: Python :: 3.4
